sparkless_testing/__init__.py
sparkless_testing/conftest.py
sparkless_testing/engine.py
sparkless_testing/parametrize.py
sparkless_testing/protocols.py
sparkless_testing/py.typed
sparkless_testing/pytest_fixtures.py
sparkless_testing/session.py
sparkless_testing/utils.py
sparkless_testing-0.2.0.dist-info/licenses/LICENSE
sparkless_testing-0.2.0.dist-info/METADATA
sparkless_testing-0.2.0.dist-info/WHEEL
sparkless_testing-0.2.0.dist-info/top_level.txt
sparkless_testing-0.2.0.dist-info/RECORD
