Metadata-Version: 2.4
Name: sparkless-testing
Version: 0.2.0
Summary: Easy testing with sparkless or PySpark on demand
Author-email: Odos Matthews <odosmatthews@gmail.com>
Maintainer-email: Odos Matthews <odosmatthews@gmail.com>
License: MIT
Project-URL: Homepage, https://github.com/eddiethedean/sparkless-testing
Project-URL: Repository, https://github.com/eddiethedean/sparkless-testing
Project-URL: Issues, https://github.com/eddiethedean/sparkless-testing/issues
Keywords: spark,pyspark,testing,pytest,sparkless,data-engineering,unit-testing,fixtures
Classifier: Development Status :: 3 - Alpha
Classifier: Intended Audience :: Developers
Classifier: License :: OSI Approved :: MIT License
Classifier: Operating System :: OS Independent
Classifier: Programming Language :: Python :: 3
Classifier: Programming Language :: Python :: 3.9
Classifier: Programming Language :: Python :: 3.10
Classifier: Programming Language :: Python :: 3.11
Classifier: Topic :: Software Development :: Testing
Classifier: Topic :: Software Development :: Libraries :: Python Modules
Requires-Python: >=3.9
License-File: LICENSE
Requires-Dist: pytest>=7.0.0
Provides-Extra: mock
Requires-Dist: sparkless>=3.19.0; extra == "mock"
Provides-Extra: pyspark
Requires-Dist: pyspark<3.6.0,>=3.5.0; extra == "pyspark"
Provides-Extra: dev
Requires-Dist: pytest>=7.0.0; extra == "dev"
Requires-Dist: pytest-cov>=4.0.0; extra == "dev"
Requires-Dist: mypy>=1.0.0; extra == "dev"
Requires-Dist: ruff>=0.4.0; extra == "dev"
Requires-Dist: sparkless>=3.19.0; extra == "dev"
Requires-Dist: pyspark<3.6.0,>=3.5.0; extra == "dev"
Dynamic: license-file
